MANIFEST.in
Pipfile
Pipfile.lock
README.md
requirements.txt
setup.cfg
setup.py
async_freesia.egg-info/PKG-INFO
async_freesia.egg-info/SOURCES.txt
async_freesia.egg-info/dependency_links.txt
async_freesia.egg-info/requires.txt
async_freesia.egg-info/top_level.txt
freesia/__init__.py
freesia/app.py
freesia/group.py
freesia/route.py
freesia/session.py
freesia/utils.py
freesia/view.py
tests/__init__.py
tests/test_groups.py
tests/test_route.py
tests/test_router.py
tests/test_view.py