Metadata-Version: 1.0
Name: async-freesia
Version: 0.1.2
Summary: A concise and lightweight web framework.✨
Home-page: https://github.com/AuraiProject/freesia
Author: ArianX
Author-email: UNKNOWN
License: MIT
Keywords: freesia,framework,backend
Platform: UNKNOWN
